modern_python_test/__init__.py
modern_python_test/console.py
modern_python_test/wikipedia.py
modern_python_test-0.1.0.dist-info/entry_points.txt
modern_python_test-0.1.0.dist-info/LICENSE
modern_python_test-0.1.0.dist-info/WHEEL
modern_python_test-0.1.0.dist-info/METADATA
modern_python_test-0.1.0.dist-info/RECORD
