Metadata-Version: 2.1
Name: modern-python-test
Version: 0.1.0
Summary: 
Author: Your Name
Author-email: you@example.com
Requires-Python: >=3.7,<4.0
Classifier: Programming Language :: Python :: 3
Classifier: Programming Language :: Python :: 3.7
Classifier: Programming Language :: Python :: 3.8
Requires-Dist: click (>=7.1.2,<8.0.0)
Requires-Dist: desert (>=2020.1.6,<2021.0.0)
Requires-Dist: marshmallow (>=3.7.1,<4.0.0)
Requires-Dist: requests (>=2.24.0,<3.0.0)
